regpnlpypi/__init__.py
regpnlpypi/backtest.py
regpnlpypi/forward_broker.py
regpnlpypi/launch.py
regpnlpypi/main.py
regpnlpypi/predict_spot.py
regpnlpypi-1.0.dist-info/METADATA
regpnlpypi-1.0.dist-info/WHEEL
regpnlpypi-1.0.dist-info/top_level.txt
regpnlpypi-1.0.dist-info/RECORD
