Metadata-Version: 2.2
Name: regpnlpypi
Version: 1.0
Requires-Dist: beautifulsoup4==4.12.3
Requires-Dist: build==1.2.1
Requires-Dist: DatastreamPy==2.0.21
Requires-Dist: debugpy==1.8.1
Requires-Dist: executing==2.0.1
Requires-Dist: Markdown==3.7
Requires-Dist: markdown-it-py==3.0.0
Requires-Dist: holidays==0.63
Requires-Dist: html5lib==1.1
Requires-Dist: matplotlib==3.8.0
Requires-Dist: matplotlib-inline==0.1.7
Requires-Dist: mypy-extensions==1.0.0
Requires-Dist: numpy==1.26.4
Requires-Dist: oauthlib==3.2.2
Requires-Dist: packaging==23.2
Requires-Dist: pip==24.3.1
Requires-Dist: pandas==2.2.3
Requires-Dist: pandas-datareader==0.10.0
Requires-Dist: pybacktestchain==0.2.1
Requires-Dist: PyDatastream==0.6.5
Requires-Dist: python-dateutil==2.8.2
Requires-Dist: requests==2.31.0
Requires-Dist: scikit-learn==1.2.2
Requires-Dist: scipy==1.11.3
Requires-Dist: statsmodels==0.14.4
Requires-Dist: streamlit==1.41.1
Requires-Dist: textblob==0.18.0.post0
Requires-Dist: types-python-dateutil==2.9.0.20241206
Requires-Dist: typing_extensions==4.12.2
Requires-Dist: urllib3==2.2.1
Requires-Dist: virtualenv==20.26.3
Requires-Dist: yfinance==0.2.51
Requires-Dist: setuptools==75.8.0
Requires-Dist: setuptools-scm==8.1.0
Requires-Dist: numba==0.60.0
Requires-Dist: pytest==8.3.4
Requires-Dist: python-json-logger==3.2.1
Requires-Dist: cloudpickle==3.1.0
Requires-Dist: sec-cik-mapper==2.1.0
Dynamic: description
Dynamic: description-content-type
Dynamic: requires-dist
